gaticos/__init__.py
gaticos/main.py
cats_test_manu_python_advanced-0.1.0.dist-info/METADATA
cats_test_manu_python_advanced-0.1.0.dist-info/WHEEL
cats_test_manu_python_advanced-0.1.0.dist-info/entry_points.txt
cats_test_manu_python_advanced-0.1.0.dist-info/RECORD
