Metadata-Version: 2.1
Name: cats-test-manu-python-advanced
Version: 0.1.0
Summary: 
Author: m.mendizabal
Requires-Python: >=3.12,<4.0
Classifier: License :: OSI Approved :: MIT License
Classifier: Operating System :: OS Independent
Classifier: Programming Language :: Python :: 3
Classifier: Programming Language :: Python :: 3.12
Requires-Dist: click (>=8.2.1,<9.0.0)
Requires-Dist: ipdb (>=0.13.13,<0.14.0)
Requires-Dist: setuptools (>=80.9.0,<81.0.0)
